openmc_track_file_processor/__init__.py
openmc_track_file_processor/core.py
openmc_track_file_processor-0.0.3.dist-info/METADATA
openmc_track_file_processor-0.0.3.dist-info/WHEEL
openmc_track_file_processor-0.0.3.dist-info/top_level.txt
openmc_track_file_processor-0.0.3.dist-info/RECORD
