Metadata-Version: 2.1
Name: openmc-track-file-processor
Version: 0.0.3
Summary: Create 3D fusion reactor CAD models based on input parameters
Home-page: https://github.com/fusion-energy/openmc_track_file_processor
Author: The Fusion Energy Development Team
Author-email: mail@jshimwell.com
License: UNKNOWN
Platform: UNKNOWN
Classifier: Natural Language :: English
Classifier: Topic :: Scientific/Engineering
Classifier: Programming Language :: Python :: 3
Classifier: Programming Language :: Python :: 3.6
Classifier: Programming Language :: Python :: 3.7
Classifier: Programming Language :: Python :: 3.8
Classifier: Programming Language :: Python :: 3.9
Classifier: License :: OSI Approved :: MIT License
Classifier: Operating System :: OS Independent
Requires-Python: >=3.6
Requires-Dist: trimesh
Requires-Dist: h5py
Requires-Dist: numpy
